<beans xmlns="http://www.springframework.org/schema/beans"
       xmlns:xsi="http://www.w3.org/2001/XMLSchema-instance"
       xmlns:context="http://www.springframework.org/schema/context"
       xsi:schemaLocation="http://www.springframework.org/schema/beans
        http://www.springframework.org/schema/beans/spring-beans.xsd
    	http://www.springframework.org/schema/context
        http://www.springframework.org/schema/context/spring-context.xsd">

    <!-- Spring容器只能有一个PropertyPlaceholderConfigurer，如果有多个属性文件，这时就看谁先谁后了，先的保留 ，后的忽略 -->
    <context:property-placeholder location="jdbc.properties"/>
    <bean id="dataSource"
          class="org.apache.commons.dbcp.BasicDataSource" destroy-method="close">
        <property name="driverClassName" value="${jdbc.driverClassName}"/>
        <property name="url" value="${jdbc.url}"/>
        <property name="username" value="${jdbc.username}"/>
        <property name="password" value="${jdbc.password}"/>
    </bean>

    <!--jdbcTemplate作为dao的属性使用 -->
    <bean id="jdbcTemplate" class="org.springframework.jdbc.core.JdbcTemplate">
        <property name="dataSource" ref="dataSource"></property>
    </bean>

    <bean id="studentDao" class="com.java1234.dao.impl.C01_JdbcTemplate_StudentDaoImpl">
        <property name="jdbcTemplate" ref="jdbcTemplate"></property>
    </bean>

    <bean id="studentService" class="com.java1234.service.impl.C01_JdbcTemplate_StudentServiceImpl">
        <property name="studentDao" ref="studentDao"></property>
    </bean>

</beans>